realeyes/face_verification/FaceVerificationLibrary.dll
realeyes/face_verification/FaceVerificationLibrary.lib
realeyes/face_verification/__init__.py
realeyes/face_verification/__init__.pyi
realeyes/face_verification/cpp.cp38-win_amd64.pyd
realeyes/face_verification/py.typed
realeyes.face_verification-1.4.4.dist-info/METADATA
realeyes.face_verification-1.4.4.dist-info/WHEEL
realeyes.face_verification-1.4.4.dist-info/top_level.txt
realeyes.face_verification-1.4.4.dist-info/RECORD
