Metadata-Version: 2.1
Name: realeyes.face-verification
Version: 1.4.4
Summary: Face Verification Library from RealEyes
Home-page: UNKNOWN
Author: Realeyes
Author-email: daniel@realeyesit.com
License: UNKNOWN
Platform: UNKNOWN
Requires-Dist: numpy >=1.10.0
